{
    "image": "generated.photos_v3_0974045.jpg",
    "faceLandmarks": {
        "mouth": [
            {
                "x": 102,
                "y": 184
            },
            {
                "x": 110,
                "y": 178
            },
            {
                "x": 120,
                "y": 176
            },
            {
                "x": 126,
                "y": 178
            },
            {
                "x": 132,
                "y": 176
            },
            {
                "x": 144,
                "y": 178
            },
            {
                "x": 154,
                "y": 184
            },
            {
                "x": 144,
                "y": 192
            },
            {
                "x": 134,
                "y": 196
            },
            {
                "x": 128,
                "y": 196
            },
            {
                "x": 120,
                "y": 196
            },
            {
                "x": 112,
                "y": 192
            },
            {
                "x": 106,
                "y": 184
            },
            {
                "x": 120,
                "y": 184
            },
            {
                "x": 126,
                "y": 184
            },
            {
                "x": 134,
                "y": 184
            },
            {
                "x": 148,
                "y": 184
            },
            {
                "x": 134,
                "y": 186
            },
            {
                "x": 126,
                "y": 186
            },
            {
                "x": 120,
                "y": 186
            }
        ],
        "right_eyebrow": [
            {
                "x": 72,
                "y": 104
            },
            {
                "x": 80,
                "y": 96
            },
            {
                "x": 92,
                "y": 94
            },
            {
                "x": 102,
                "y": 98
            },
            {
                "x": 114,
                "y": 104
            }
        ],
        "left_eyebrow": [
            {
                "x": 136,
                "y": 104
            },
            {
                "x": 148,
                "y": 98
            },
            {
                "x": 162,
                "y": 94
            },
            {
                "x": 176,
                "y": 96
            },
            {
                "x": 184,
                "y": 106
            }
        ],
        "right_eye": [
            {
                "x": 84,
                "y": 122
            },
            {
                "x": 92,
                "y": 116
            },
            {
                "x": 100,
                "y": 116
            },
            {
                "x": 110,
                "y": 124
            },
            {
                "x": 100,
                "y": 126
            },
            {
                "x": 90,
                "y": 126
            }
        ],
        "left_eye": [
            {
                "x": 144,
                "y": 124
            },
            {
                "x": 152,
                "y": 116
            },
            {
                "x": 162,
                "y": 116
            },
            {
                "x": 170,
                "y": 122
            },
            {
                "x": 164,
                "y": 126
            },
            {
                "x": 154,
                "y": 126
            }
        ],
        "nose": [
            {
                "x": 126,
                "y": 118
            },
            {
                "x": 126,
                "y": 130
            },
            {
                "x": 124,
                "y": 142
            },
            {
                "x": 124,
                "y": 152
            },
            {
                "x": 114,
                "y": 162
            },
            {
                "x": 120,
                "y": 164
            },
            {
                "x": 126,
                "y": 166
            },
            {
                "x": 132,
                "y": 164
            }
        ],
        "jaw": [
            {
                "x": 64,
                "y": 122
            },
            {
                "x": 66,
                "y": 140
            },
            {
                "x": 68,
                "y": 156
            },
            {
                "x": 72,
                "y": 172
            },
            {
                "x": 76,
                "y": 188
            },
            {
                "x": 84,
                "y": 200
            },
            {
                "x": 96,
                "y": 212
            },
            {
                "x": 112,
                "y": 222
            },
            {
                "x": 128,
                "y": 226
            },
            {
                "x": 146,
                "y": 224
            },
            {
                "x": 162,
                "y": 216
            },
            {
                "x": 176,
                "y": 206
            },
            {
                "x": 184,
                "y": 192
            },
            {
                "x": 190,
                "y": 174
            },
            {
                "x": 192,
                "y": 158
            },
            {
                "x": 196,
                "y": 140
            },
            {
                "x": 198,
                "y": 122
            }
        ]
    },
    "faceAttributes": {
        "headPose": {
            "pitch": -2.77,
            "roll": -0.07,
            "yaw": -3.86
        },
        "gender": {
            "male": 0.13,
            "female": 0.87
        },
        "makeup": {
            "eyeMakeup": 0.82,
            "lipMakeup": 0.76
        },
        "emotion": {
            "anger": 0.01,
            "contempt": 0.04,
            "disgust": 0.03,
            "fear": 0.0,
            "happiness": 0.41,
            "neutral": 0.44,
            "sadness": 0.05,
            "surprise": 0.02
        },
        "facialHair": {
            "moustache": -0.01,
            "beard": -0.0,
            "sideburns": -0.01
        },
        "hair": {
            "hairColor": [
                {
                    "name": "brown",
                    "confidence": 0.94
                },
                {
                    "name": "black",
                    "confidence": 0.6
                },
                {
                    "name": "blond",
                    "confidence": 0.32
                },
                {
                    "name": "red",
                    "confidence": 0.33
                },
                {
                    "name": "gray",
                    "confidence": 0.23
                },
                {
                    "name": "other",
                    "confidence": 0.16
                }
            ],
            "hairLength": [
                {
                    "name": "Long",
                    "confidence": 0.03
                },
                {
                    "name": "Medium",
                    "confidence": 0.9
                },
                {
                    "name": "Short",
                    "confidence": 0.0
                }
            ],
            "bald": 0.13
        },
        "occlusion": {
            "foreheadOccluded": -0.04,
            "eyeOccluded": -0.0,
            "mouthOccluded": -0.0
        },
        "ethnicity": [
            {
                "name": "asian",
                "confidence": 0.33
            },
            {
                "name": "black",
                "confidence": 0.0
            },
            {
                "name": "latino",
                "confidence": 0.02
            },
            {
                "name": "white",
                "confidence": 0.65
            }
        ],
        "eye_color": [
            {
                "name": "Blue",
                "confidence": 0.05
            },
            {
                "name": "Brown",
                "confidence": 0.21
            },
            {
                "name": "Green",
                "confidence": 0.17
            },
            {
                "name": "Grey",
                "confidence": 0.19
            }
        ],
        "smile": 0.41,
        "age": 26.12
    },
    "bug_probability": 0.01
}