{
    "image": "generated.photos_v3_0139029_0652990_0283189.jpg",
    "faceLandmarks": {
        "mouth": [
            {
                "x": 100,
                "y": 184
            },
            {
                "x": 108,
                "y": 178
            },
            {
                "x": 116,
                "y": 174
            },
            {
                "x": 122,
                "y": 176
            },
            {
                "x": 128,
                "y": 174
            },
            {
                "x": 142,
                "y": 178
            },
            {
                "x": 154,
                "y": 184
            },
            {
                "x": 142,
                "y": 196
            },
            {
                "x": 130,
                "y": 202
            },
            {
                "x": 124,
                "y": 202
            },
            {
                "x": 116,
                "y": 200
            },
            {
                "x": 108,
                "y": 196
            },
            {
                "x": 106,
                "y": 186
            },
            {
                "x": 116,
                "y": 186
            },
            {
                "x": 122,
                "y": 186
            },
            {
                "x": 130,
                "y": 186
            },
            {
                "x": 148,
                "y": 186
            },
            {
                "x": 130,
                "y": 188
            },
            {
                "x": 124,
                "y": 188
            },
            {
                "x": 116,
                "y": 186
            }
        ],
        "right_eyebrow": [
            {
                "x": 76,
                "y": 100
            },
            {
                "x": 82,
                "y": 92
            },
            {
                "x": 92,
                "y": 92
            },
            {
                "x": 100,
                "y": 94
            },
            {
                "x": 110,
                "y": 98
            }
        ],
        "left_eyebrow": [
            {
                "x": 138,
                "y": 98
            },
            {
                "x": 150,
                "y": 92
            },
            {
                "x": 162,
                "y": 90
            },
            {
                "x": 174,
                "y": 92
            },
            {
                "x": 184,
                "y": 100
            }
        ],
        "right_eye": [
            {
                "x": 86,
                "y": 118
            },
            {
                "x": 92,
                "y": 116
            },
            {
                "x": 100,
                "y": 116
            },
            {
                "x": 108,
                "y": 122
            },
            {
                "x": 100,
                "y": 124
            },
            {
                "x": 90,
                "y": 124
            }
        ],
        "left_eye": [
            {
                "x": 144,
                "y": 122
            },
            {
                "x": 152,
                "y": 116
            },
            {
                "x": 160,
                "y": 116
            },
            {
                "x": 170,
                "y": 120
            },
            {
                "x": 162,
                "y": 124
            },
            {
                "x": 152,
                "y": 124
            }
        ],
        "nose": [
            {
                "x": 124,
                "y": 118
            },
            {
                "x": 122,
                "y": 130
            },
            {
                "x": 122,
                "y": 140
            },
            {
                "x": 120,
                "y": 152
            },
            {
                "x": 108,
                "y": 160
            },
            {
                "x": 114,
                "y": 164
            },
            {
                "x": 122,
                "y": 166
            },
            {
                "x": 130,
                "y": 164
            }
        ],
        "jaw": [
            {
                "x": 70,
                "y": 116
            },
            {
                "x": 70,
                "y": 132
            },
            {
                "x": 72,
                "y": 148
            },
            {
                "x": 76,
                "y": 164
            },
            {
                "x": 80,
                "y": 182
            },
            {
                "x": 86,
                "y": 196
            },
            {
                "x": 96,
                "y": 212
            },
            {
                "x": 108,
                "y": 224
            },
            {
                "x": 126,
                "y": 230
            },
            {
                "x": 146,
                "y": 228
            },
            {
                "x": 166,
                "y": 220
            },
            {
                "x": 182,
                "y": 208
            },
            {
                "x": 194,
                "y": 194
            },
            {
                "x": 202,
                "y": 174
            },
            {
                "x": 206,
                "y": 154
            },
            {
                "x": 208,
                "y": 134
            },
            {
                "x": 208,
                "y": 112
            }
        ]
    },
    "faceAttributes": {
        "headPose": {
            "pitch": -4.95,
            "roll": -0.12,
            "yaw": -14.14
        },
        "gender": {
            "male": 0.42,
            "female": 0.58
        },
        "makeup": {
            "eyeMakeup": 0.56,
            "lipMakeup": 0.47
        },
        "emotion": {
            "anger": -0.0,
            "contempt": 0.03,
            "disgust": 0.01,
            "fear": 0.0,
            "happiness": 0.54,
            "neutral": 0.37,
            "sadness": 0.03,
            "surprise": 0.01
        },
        "facialHair": {
            "moustache": 0.07,
            "beard": 0.07,
            "sideburns": 0.04
        },
        "hair": {
            "hairColor": [
                {
                    "name": "brown",
                    "confidence": 0.91
                },
                {
                    "name": "black",
                    "confidence": 0.93
                },
                {
                    "name": "blond",
                    "confidence": 0.04
                },
                {
                    "name": "red",
                    "confidence": 0.15
                },
                {
                    "name": "gray",
                    "confidence": 0.3
                },
                {
                    "name": "other",
                    "confidence": 0.28
                }
            ],
            "hairLength": [
                {
                    "name": "Long",
                    "confidence": 0.35
                },
                {
                    "name": "Medium",
                    "confidence": 0.27
                },
                {
                    "name": "Short",
                    "confidence": 0.06
                }
            ],
            "bald": 0.15
        },
        "occlusion": {
            "foreheadOccluded": 0.04,
            "eyeOccluded": -0.0,
            "mouthOccluded": -0.0
        },
        "ethnicity": [
            {
                "name": "asian",
                "confidence": 0.04
            },
            {
                "name": "black",
                "confidence": 0.49
            },
            {
                "name": "latino",
                "confidence": 0.45
            },
            {
                "name": "white",
                "confidence": 0.01
            }
        ],
        "eye_color": [
            {
                "name": "Blue",
                "confidence": 0.04
            },
            {
                "name": "Brown",
                "confidence": 0.92
            },
            {
                "name": "Green",
                "confidence": 0.02
            },
            {
                "name": "Grey",
                "confidence": 0.02
            }
        ],
        "smile": 0.54,
        "age": 32.66
    },
    "bug_probability": 0.1
}