{
    "image": "generated.photos_v3_0441306.jpg",
    "faceLandmarks": {
        "mouth": [
            {
                "x": 106,
                "y": 190
            },
            {
                "x": 116,
                "y": 182
            },
            {
                "x": 128,
                "y": 178
            },
            {
                "x": 134,
                "y": 180
            },
            {
                "x": 142,
                "y": 178
            },
            {
                "x": 148,
                "y": 182
            },
            {
                "x": 150,
                "y": 190
            },
            {
                "x": 148,
                "y": 200
            },
            {
                "x": 142,
                "y": 204
            },
            {
                "x": 134,
                "y": 204
            },
            {
                "x": 126,
                "y": 204
            },
            {
                "x": 116,
                "y": 200
            },
            {
                "x": 110,
                "y": 190
            },
            {
                "x": 126,
                "y": 188
            },
            {
                "x": 134,
                "y": 188
            },
            {
                "x": 140,
                "y": 188
            },
            {
                "x": 148,
                "y": 190
            },
            {
                "x": 140,
                "y": 190
            },
            {
                "x": 134,
                "y": 192
            },
            {
                "x": 126,
                "y": 192
            }
        ],
        "right_eyebrow": [
            {
                "x": 74,
                "y": 108
            },
            {
                "x": 82,
                "y": 100
            },
            {
                "x": 94,
                "y": 94
            },
            {
                "x": 108,
                "y": 96
            },
            {
                "x": 120,
                "y": 100
            }
        ],
        "left_eyebrow": [
            {
                "x": 144,
                "y": 100
            },
            {
                "x": 152,
                "y": 96
            },
            {
                "x": 162,
                "y": 96
            },
            {
                "x": 170,
                "y": 100
            },
            {
                "x": 172,
                "y": 108
            }
        ],
        "right_eye": [
            {
                "x": 88,
                "y": 120
            },
            {
                "x": 96,
                "y": 116
            },
            {
                "x": 104,
                "y": 116
            },
            {
                "x": 112,
                "y": 122
            },
            {
                "x": 104,
                "y": 124
            },
            {
                "x": 94,
                "y": 124
            }
        ],
        "left_eye": [
            {
                "x": 142,
                "y": 122
            },
            {
                "x": 150,
                "y": 118
            },
            {
                "x": 158,
                "y": 116
            },
            {
                "x": 162,
                "y": 122
            },
            {
                "x": 158,
                "y": 124
            },
            {
                "x": 150,
                "y": 124
            }
        ],
        "nose": [
            {
                "x": 132,
                "y": 118
            },
            {
                "x": 134,
                "y": 130
            },
            {
                "x": 136,
                "y": 140
            },
            {
                "x": 138,
                "y": 152
            },
            {
                "x": 118,
                "y": 162
            },
            {
                "x": 126,
                "y": 164
            },
            {
                "x": 136,
                "y": 166
            },
            {
                "x": 142,
                "y": 164
            }
        ],
        "jaw": [
            {
                "x": 44,
                "y": 128
            },
            {
                "x": 44,
                "y": 148
            },
            {
                "x": 46,
                "y": 168
            },
            {
                "x": 52,
                "y": 188
            },
            {
                "x": 60,
                "y": 206
            },
            {
                "x": 76,
                "y": 218
            },
            {
                "x": 92,
                "y": 230
            },
            {
                "x": 112,
                "y": 236
            },
            {
                "x": 132,
                "y": 238
            },
            {
                "x": 148,
                "y": 232
            },
            {
                "x": 158,
                "y": 222
            },
            {
                "x": 166,
                "y": 206
            },
            {
                "x": 170,
                "y": 190
            },
            {
                "x": 172,
                "y": 174
            },
            {
                "x": 176,
                "y": 156
            },
            {
                "x": 176,
                "y": 142
            },
            {
                "x": 174,
                "y": 126
            }
        ]
    },
    "faceAttributes": {
        "headPose": {
            "pitch": 5.23,
            "roll": 0.99,
            "yaw": 15.09
        },
        "gender": {
            "male": 0.82,
            "female": 0.18
        },
        "makeup": {
            "eyeMakeup": 0.17,
            "lipMakeup": 0.14
        },
        "emotion": {
            "anger": -0.0,
            "contempt": 0.02,
            "disgust": -0.0,
            "fear": 0.0,
            "happiness": 0.28,
            "neutral": 0.64,
            "sadness": 0.03,
            "surprise": 0.05
        },
        "facialHair": {
            "moustache": 0.23,
            "beard": 0.24,
            "sideburns": 0.16
        },
        "hair": {
            "hairColor": [
                {
                    "name": "brown",
                    "confidence": 0.73
                },
                {
                    "name": "black",
                    "confidence": 0.68
                },
                {
                    "name": "blond",
                    "confidence": 0.37
                },
                {
                    "name": "red",
                    "confidence": 0.15
                },
                {
                    "name": "gray",
                    "confidence": 0.53
                },
                {
                    "name": "other",
                    "confidence": 0.34
                }
            ],
            "hairLength": [
                {
                    "name": "Long",
                    "confidence": 0.0
                },
                {
                    "name": "Medium",
                    "confidence": 0.05
                },
                {
                    "name": "Short",
                    "confidence": 0.98
                }
            ],
            "bald": 0.18
        },
        "occlusion": {
            "foreheadOccluded": 0.14,
            "eyeOccluded": 0.0,
            "mouthOccluded": 0.0
        },
        "ethnicity": [
            {
                "name": "asian",
                "confidence": 0.14
            },
            {
                "name": "black",
                "confidence": 0.44
            },
            {
                "name": "latino",
                "confidence": 0.31
            },
            {
                "name": "white",
                "confidence": 0.11
            }
        ],
        "eye_color": [
            {
                "name": "Blue",
                "confidence": 0.03
            },
            {
                "name": "Brown",
                "confidence": 0.92
            },
            {
                "name": "Green",
                "confidence": 0.01
            },
            {
                "name": "Grey",
                "confidence": 0.03
            }
        ],
        "smile": 0.28,
        "age": 41.08
    },
    "bug_probability": 0.0
}