{
    "image": "generated.photos_v3_0046689.jpg",
    "faceLandmarks": {
        "mouth": [
            {
                "x": 100,
                "y": 186
            },
            {
                "x": 110,
                "y": 182
            },
            {
                "x": 118,
                "y": 180
            },
            {
                "x": 126,
                "y": 182
            },
            {
                "x": 134,
                "y": 180
            },
            {
                "x": 144,
                "y": 182
            },
            {
                "x": 156,
                "y": 186
            },
            {
                "x": 144,
                "y": 194
            },
            {
                "x": 136,
                "y": 196
            },
            {
                "x": 128,
                "y": 198
            },
            {
                "x": 120,
                "y": 196
            },
            {
                "x": 110,
                "y": 194
            },
            {
                "x": 104,
                "y": 188
            },
            {
                "x": 118,
                "y": 186
            },
            {
                "x": 126,
                "y": 188
            },
            {
                "x": 134,
                "y": 186
            },
            {
                "x": 152,
                "y": 188
            },
            {
                "x": 134,
                "y": 188
            },
            {
                "x": 128,
                "y": 188
            },
            {
                "x": 120,
                "y": 188
            }
        ],
        "right_eyebrow": [
            {
                "x": 70,
                "y": 110
            },
            {
                "x": 78,
                "y": 100
            },
            {
                "x": 90,
                "y": 96
            },
            {
                "x": 102,
                "y": 98
            },
            {
                "x": 116,
                "y": 104
            }
        ],
        "left_eyebrow": [
            {
                "x": 138,
                "y": 104
            },
            {
                "x": 150,
                "y": 98
            },
            {
                "x": 162,
                "y": 96
            },
            {
                "x": 176,
                "y": 100
            },
            {
                "x": 184,
                "y": 110
            }
        ],
        "right_eye": [
            {
                "x": 84,
                "y": 122
            },
            {
                "x": 92,
                "y": 116
            },
            {
                "x": 100,
                "y": 116
            },
            {
                "x": 108,
                "y": 122
            },
            {
                "x": 100,
                "y": 124
            },
            {
                "x": 92,
                "y": 124
            }
        ],
        "left_eye": [
            {
                "x": 144,
                "y": 122
            },
            {
                "x": 152,
                "y": 116
            },
            {
                "x": 162,
                "y": 116
            },
            {
                "x": 170,
                "y": 122
            },
            {
                "x": 162,
                "y": 124
            },
            {
                "x": 152,
                "y": 124
            }
        ],
        "nose": [
            {
                "x": 126,
                "y": 118
            },
            {
                "x": 126,
                "y": 130
            },
            {
                "x": 126,
                "y": 142
            },
            {
                "x": 126,
                "y": 156
            },
            {
                "x": 112,
                "y": 164
            },
            {
                "x": 118,
                "y": 166
            },
            {
                "x": 126,
                "y": 168
            },
            {
                "x": 134,
                "y": 166
            }
        ],
        "jaw": [
            {
                "x": 56,
                "y": 122
            },
            {
                "x": 56,
                "y": 142
            },
            {
                "x": 60,
                "y": 160
            },
            {
                "x": 62,
                "y": 178
            },
            {
                "x": 68,
                "y": 196
            },
            {
                "x": 78,
                "y": 210
            },
            {
                "x": 92,
                "y": 224
            },
            {
                "x": 108,
                "y": 232
            },
            {
                "x": 128,
                "y": 236
            },
            {
                "x": 148,
                "y": 234
            },
            {
                "x": 164,
                "y": 224
            },
            {
                "x": 178,
                "y": 212
            },
            {
                "x": 188,
                "y": 196
            },
            {
                "x": 192,
                "y": 178
            },
            {
                "x": 196,
                "y": 160
            },
            {
                "x": 198,
                "y": 142
            },
            {
                "x": 198,
                "y": 124
            }
        ]
    },
    "faceAttributes": {
        "headPose": {
            "pitch": 0.52,
            "roll": 0.02,
            "yaw": -0.91
        },
        "gender": {
            "male": 0.89,
            "female": 0.11
        },
        "makeup": {
            "eyeMakeup": 0.27,
            "lipMakeup": 0.2
        },
        "emotion": {
            "anger": 0.01,
            "contempt": 0.03,
            "disgust": 0.02,
            "fear": -0.0,
            "happiness": 0.51,
            "neutral": 0.41,
            "sadness": 0.04,
            "surprise": -0.02
        },
        "facialHair": {
            "moustache": 0.14,
            "beard": 0.14,
            "sideburns": 0.1
        },
        "hair": {
            "hairColor": [
                {
                    "name": "brown",
                    "confidence": 0.86
                },
                {
                    "name": "black",
                    "confidence": 0.87
                },
                {
                    "name": "blond",
                    "confidence": 0.13
                },
                {
                    "name": "red",
                    "confidence": 0.11
                },
                {
                    "name": "gray",
                    "confidence": 0.4
                },
                {
                    "name": "other",
                    "confidence": 0.26
                }
            ],
            "hairLength": [
                {
                    "name": "Long",
                    "confidence": 0.01
                },
                {
                    "name": "Medium",
                    "confidence": 0.02
                },
                {
                    "name": "Short",
                    "confidence": 0.99
                }
            ],
            "bald": 0.13
        },
        "occlusion": {
            "foreheadOccluded": -0.01,
            "eyeOccluded": 0.0,
            "mouthOccluded": 0.0
        },
        "ethnicity": [
            {
                "name": "asian",
                "confidence": 0.17
            },
            {
                "name": "black",
                "confidence": 0.01
            },
            {
                "name": "latino",
                "confidence": 0.4
            },
            {
                "name": "white",
                "confidence": 0.42
            }
        ],
        "eye_color": [
            {
                "name": "Blue",
                "confidence": 0.01
            },
            {
                "name": "Brown",
                "confidence": 0.86
            },
            {
                "name": "Green",
                "confidence": 0.08
            },
            {
                "name": "Grey",
                "confidence": 0.12
            }
        ],
        "smile": 0.51,
        "age": 34.63
    },
    "bug_probability": 0.0
}