{
    "image": "generated.photos_v3_0975950.jpg",
    "faceLandmarks": {
        "mouth": [
            {
                "x": 100,
                "y": 186
            },
            {
                "x": 112,
                "y": 178
            },
            {
                "x": 122,
                "y": 174
            },
            {
                "x": 130,
                "y": 176
            },
            {
                "x": 138,
                "y": 174
            },
            {
                "x": 146,
                "y": 178
            },
            {
                "x": 152,
                "y": 186
            },
            {
                "x": 146,
                "y": 194
            },
            {
                "x": 138,
                "y": 198
            },
            {
                "x": 130,
                "y": 200
            },
            {
                "x": 122,
                "y": 198
            },
            {
                "x": 110,
                "y": 194
            },
            {
                "x": 106,
                "y": 186
            },
            {
                "x": 122,
                "y": 186
            },
            {
                "x": 130,
                "y": 186
            },
            {
                "x": 138,
                "y": 186
            },
            {
                "x": 148,
                "y": 186
            },
            {
                "x": 138,
                "y": 188
            },
            {
                "x": 130,
                "y": 188
            },
            {
                "x": 122,
                "y": 186
            }
        ],
        "right_eyebrow": [
            {
                "x": 70,
                "y": 104
            },
            {
                "x": 80,
                "y": 96
            },
            {
                "x": 92,
                "y": 94
            },
            {
                "x": 106,
                "y": 96
            },
            {
                "x": 118,
                "y": 102
            }
        ],
        "left_eyebrow": [
            {
                "x": 140,
                "y": 102
            },
            {
                "x": 152,
                "y": 96
            },
            {
                "x": 162,
                "y": 96
            },
            {
                "x": 172,
                "y": 98
            },
            {
                "x": 180,
                "y": 106
            }
        ],
        "right_eye": [
            {
                "x": 84,
                "y": 120
            },
            {
                "x": 92,
                "y": 116
            },
            {
                "x": 102,
                "y": 116
            },
            {
                "x": 110,
                "y": 124
            },
            {
                "x": 102,
                "y": 126
            },
            {
                "x": 92,
                "y": 126
            }
        ],
        "left_eye": [
            {
                "x": 144,
                "y": 124
            },
            {
                "x": 152,
                "y": 116
            },
            {
                "x": 162,
                "y": 116
            },
            {
                "x": 168,
                "y": 120
            },
            {
                "x": 162,
                "y": 126
            },
            {
                "x": 152,
                "y": 126
            }
        ],
        "nose": [
            {
                "x": 130,
                "y": 120
            },
            {
                "x": 130,
                "y": 132
            },
            {
                "x": 132,
                "y": 144
            },
            {
                "x": 132,
                "y": 154
            },
            {
                "x": 118,
                "y": 164
            },
            {
                "x": 124,
                "y": 166
            },
            {
                "x": 130,
                "y": 168
            },
            {
                "x": 136,
                "y": 166
            }
        ],
        "jaw": [
            {
                "x": 50,
                "y": 124
            },
            {
                "x": 52,
                "y": 142
            },
            {
                "x": 54,
                "y": 160
            },
            {
                "x": 56,
                "y": 178
            },
            {
                "x": 64,
                "y": 194
            },
            {
                "x": 76,
                "y": 208
            },
            {
                "x": 90,
                "y": 220
            },
            {
                "x": 108,
                "y": 228
            },
            {
                "x": 126,
                "y": 230
            },
            {
                "x": 144,
                "y": 226
            },
            {
                "x": 158,
                "y": 216
            },
            {
                "x": 170,
                "y": 204
            },
            {
                "x": 178,
                "y": 190
            },
            {
                "x": 182,
                "y": 172
            },
            {
                "x": 186,
                "y": 156
            },
            {
                "x": 186,
                "y": 138
            },
            {
                "x": 186,
                "y": 122
            }
        ]
    },
    "faceAttributes": {
        "headPose": {
            "pitch": -0.73,
            "roll": 0.32,
            "yaw": 7.26
        },
        "gender": {
            "male": 0.13,
            "female": 0.87
        },
        "makeup": {
            "eyeMakeup": 0.88,
            "lipMakeup": 0.74
        },
        "emotion": {
            "anger": -0.0,
            "contempt": 0.03,
            "disgust": 0.02,
            "fear": 0.0,
            "happiness": 0.58,
            "neutral": 0.32,
            "sadness": 0.03,
            "surprise": 0.03
        },
        "facialHair": {
            "moustache": 0.03,
            "beard": 0.03,
            "sideburns": 0.02
        },
        "hair": {
            "hairColor": [
                {
                    "name": "brown",
                    "confidence": 0.94
                },
                {
                    "name": "black",
                    "confidence": 0.82
                },
                {
                    "name": "blond",
                    "confidence": 0.13
                },
                {
                    "name": "red",
                    "confidence": 0.19
                },
                {
                    "name": "gray",
                    "confidence": 0.25
                },
                {
                    "name": "other",
                    "confidence": 0.21
                }
            ],
            "hairLength": [
                {
                    "name": "Long",
                    "confidence": 0.1
                },
                {
                    "name": "Medium",
                    "confidence": 0.68
                },
                {
                    "name": "Short",
                    "confidence": 0.02
                }
            ],
            "bald": 0.1
        },
        "occlusion": {
            "foreheadOccluded": -0.0,
            "eyeOccluded": -0.0,
            "mouthOccluded": -0.0
        },
        "ethnicity": [
            {
                "name": "asian",
                "confidence": 0.61
            },
            {
                "name": "black",
                "confidence": 0.0
            },
            {
                "name": "latino",
                "confidence": 0.25
            },
            {
                "name": "white",
                "confidence": 0.14
            }
        ],
        "eye_color": [
            {
                "name": "Blue",
                "confidence": 0.03
            },
            {
                "name": "Brown",
                "confidence": 0.84
            },
            {
                "name": "Green",
                "confidence": 0.04
            },
            {
                "name": "Grey",
                "confidence": 0.08
            }
        ],
        "smile": 0.58,
        "age": 27.14
    },
    "bug_probability": 0.05
}