{
    "image": "generated.photos_v3_0601778.jpg",
    "faceLandmarks": {
        "mouth": [
            {
                "x": 102,
                "y": 188
            },
            {
                "x": 110,
                "y": 182
            },
            {
                "x": 118,
                "y": 180
            },
            {
                "x": 126,
                "y": 182
            },
            {
                "x": 134,
                "y": 180
            },
            {
                "x": 142,
                "y": 182
            },
            {
                "x": 152,
                "y": 188
            },
            {
                "x": 144,
                "y": 196
            },
            {
                "x": 134,
                "y": 200
            },
            {
                "x": 126,
                "y": 202
            },
            {
                "x": 118,
                "y": 200
            },
            {
                "x": 110,
                "y": 194
            },
            {
                "x": 106,
                "y": 188
            },
            {
                "x": 118,
                "y": 188
            },
            {
                "x": 126,
                "y": 190
            },
            {
                "x": 134,
                "y": 188
            },
            {
                "x": 148,
                "y": 188
            },
            {
                "x": 134,
                "y": 188
            },
            {
                "x": 126,
                "y": 190
            },
            {
                "x": 118,
                "y": 188
            }
        ],
        "right_eyebrow": [
            {
                "x": 72,
                "y": 110
            },
            {
                "x": 80,
                "y": 100
            },
            {
                "x": 92,
                "y": 98
            },
            {
                "x": 104,
                "y": 100
            },
            {
                "x": 116,
                "y": 104
            }
        ],
        "left_eyebrow": [
            {
                "x": 136,
                "y": 104
            },
            {
                "x": 148,
                "y": 100
            },
            {
                "x": 162,
                "y": 98
            },
            {
                "x": 174,
                "y": 102
            },
            {
                "x": 184,
                "y": 110
            }
        ],
        "right_eye": [
            {
                "x": 86,
                "y": 120
            },
            {
                "x": 92,
                "y": 116
            },
            {
                "x": 100,
                "y": 116
            },
            {
                "x": 108,
                "y": 122
            },
            {
                "x": 100,
                "y": 124
            },
            {
                "x": 92,
                "y": 124
            }
        ],
        "left_eye": [
            {
                "x": 144,
                "y": 122
            },
            {
                "x": 152,
                "y": 116
            },
            {
                "x": 162,
                "y": 116
            },
            {
                "x": 168,
                "y": 122
            },
            {
                "x": 162,
                "y": 124
            },
            {
                "x": 152,
                "y": 124
            }
        ],
        "nose": [
            {
                "x": 126,
                "y": 118
            },
            {
                "x": 126,
                "y": 132
            },
            {
                "x": 126,
                "y": 144
            },
            {
                "x": 126,
                "y": 158
            },
            {
                "x": 112,
                "y": 164
            },
            {
                "x": 118,
                "y": 166
            },
            {
                "x": 126,
                "y": 170
            },
            {
                "x": 134,
                "y": 166
            }
        ],
        "jaw": [
            {
                "x": 64,
                "y": 120
            },
            {
                "x": 64,
                "y": 140
            },
            {
                "x": 68,
                "y": 158
            },
            {
                "x": 70,
                "y": 176
            },
            {
                "x": 76,
                "y": 192
            },
            {
                "x": 86,
                "y": 206
            },
            {
                "x": 98,
                "y": 220
            },
            {
                "x": 110,
                "y": 230
            },
            {
                "x": 128,
                "y": 234
            },
            {
                "x": 146,
                "y": 232
            },
            {
                "x": 160,
                "y": 222
            },
            {
                "x": 172,
                "y": 208
            },
            {
                "x": 182,
                "y": 194
            },
            {
                "x": 186,
                "y": 178
            },
            {
                "x": 190,
                "y": 158
            },
            {
                "x": 192,
                "y": 140
            },
            {
                "x": 194,
                "y": 120
            }
        ]
    },
    "faceAttributes": {
        "headPose": {
            "pitch": -4.41,
            "roll": -0.06,
            "yaw": -2.35
        },
        "gender": {
            "male": 0.87,
            "female": 0.13
        },
        "makeup": {
            "eyeMakeup": 0.28,
            "lipMakeup": 0.22
        },
        "emotion": {
            "anger": 0.0,
            "contempt": 0.02,
            "disgust": 0.01,
            "fear": -0.0,
            "happiness": 0.44,
            "neutral": 0.5,
            "sadness": 0.01,
            "surprise": 0.01
        },
        "facialHair": {
            "moustache": 0.2,
            "beard": 0.2,
            "sideburns": 0.13
        },
        "hair": {
            "hairColor": [
                {
                    "name": "brown",
                    "confidence": 0.87
                },
                {
                    "name": "black",
                    "confidence": 0.93
                },
                {
                    "name": "blond",
                    "confidence": 0.1
                },
                {
                    "name": "red",
                    "confidence": 0.12
                },
                {
                    "name": "gray",
                    "confidence": 0.35
                },
                {
                    "name": "other",
                    "confidence": 0.3
                }
            ],
            "hairLength": [
                {
                    "name": "Long",
                    "confidence": 0.01
                },
                {
                    "name": "Medium",
                    "confidence": 0.01
                },
                {
                    "name": "Short",
                    "confidence": 0.99
                }
            ],
            "bald": 0.15
        },
        "occlusion": {
            "foreheadOccluded": 0.05,
            "eyeOccluded": -0.0,
            "mouthOccluded": -0.0
        },
        "ethnicity": [
            {
                "name": "asian",
                "confidence": 0.04
            },
            {
                "name": "black",
                "confidence": 0.02
            },
            {
                "name": "latino",
                "confidence": 0.9
            },
            {
                "name": "white",
                "confidence": 0.05
            }
        ],
        "eye_color": [
            {
                "name": "Blue",
                "confidence": 0.03
            },
            {
                "name": "Brown",
                "confidence": 0.87
            },
            {
                "name": "Green",
                "confidence": 0.04
            },
            {
                "name": "Grey",
                "confidence": 0.04
            }
        ],
        "smile": 0.44,
        "age": 29.26
    },
    "bug_probability": 0.03
}