{
    "image": "generated.photos_v3_0158479.jpg",
    "faceLandmarks": {
        "mouth": [
            {
                "x": 100,
                "y": 184
            },
            {
                "x": 112,
                "y": 178
            },
            {
                "x": 120,
                "y": 172
            },
            {
                "x": 128,
                "y": 174
            },
            {
                "x": 134,
                "y": 172
            },
            {
                "x": 142,
                "y": 178
            },
            {
                "x": 152,
                "y": 186
            },
            {
                "x": 142,
                "y": 190
            },
            {
                "x": 134,
                "y": 192
            },
            {
                "x": 128,
                "y": 194
            },
            {
                "x": 120,
                "y": 192
            },
            {
                "x": 110,
                "y": 190
            },
            {
                "x": 106,
                "y": 184
            },
            {
                "x": 120,
                "y": 182
            },
            {
                "x": 128,
                "y": 182
            },
            {
                "x": 132,
                "y": 182
            },
            {
                "x": 146,
                "y": 186
            },
            {
                "x": 134,
                "y": 182
            },
            {
                "x": 128,
                "y": 184
            },
            {
                "x": 120,
                "y": 182
            }
        ],
        "right_eyebrow": [
            {
                "x": 70,
                "y": 104
            },
            {
                "x": 80,
                "y": 98
            },
            {
                "x": 90,
                "y": 94
            },
            {
                "x": 102,
                "y": 96
            },
            {
                "x": 114,
                "y": 100
            }
        ],
        "left_eyebrow": [
            {
                "x": 142,
                "y": 100
            },
            {
                "x": 154,
                "y": 94
            },
            {
                "x": 166,
                "y": 94
            },
            {
                "x": 176,
                "y": 98
            },
            {
                "x": 184,
                "y": 108
            }
        ],
        "right_eye": [
            {
                "x": 84,
                "y": 122
            },
            {
                "x": 92,
                "y": 116
            },
            {
                "x": 100,
                "y": 116
            },
            {
                "x": 108,
                "y": 122
            },
            {
                "x": 100,
                "y": 124
            },
            {
                "x": 92,
                "y": 124
            }
        ],
        "left_eye": [
            {
                "x": 146,
                "y": 122
            },
            {
                "x": 154,
                "y": 116
            },
            {
                "x": 162,
                "y": 116
            },
            {
                "x": 168,
                "y": 122
            },
            {
                "x": 162,
                "y": 124
            },
            {
                "x": 154,
                "y": 124
            }
        ],
        "nose": [
            {
                "x": 128,
                "y": 116
            },
            {
                "x": 128,
                "y": 126
            },
            {
                "x": 128,
                "y": 134
            },
            {
                "x": 128,
                "y": 144
            },
            {
                "x": 116,
                "y": 158
            },
            {
                "x": 122,
                "y": 160
            },
            {
                "x": 128,
                "y": 160
            },
            {
                "x": 134,
                "y": 160
            }
        ],
        "jaw": [
            {
                "x": 58,
                "y": 130
            },
            {
                "x": 60,
                "y": 146
            },
            {
                "x": 60,
                "y": 162
            },
            {
                "x": 62,
                "y": 180
            },
            {
                "x": 66,
                "y": 196
            },
            {
                "x": 76,
                "y": 210
            },
            {
                "x": 88,
                "y": 220
            },
            {
                "x": 106,
                "y": 228
            },
            {
                "x": 124,
                "y": 230
            },
            {
                "x": 142,
                "y": 228
            },
            {
                "x": 160,
                "y": 222
            },
            {
                "x": 174,
                "y": 212
            },
            {
                "x": 182,
                "y": 198
            },
            {
                "x": 186,
                "y": 182
            },
            {
                "x": 190,
                "y": 166
            },
            {
                "x": 192,
                "y": 148
            },
            {
                "x": 194,
                "y": 132
            }
        ]
    },
    "faceAttributes": {
        "headPose": {
            "pitch": 9.67,
            "roll": 0.11,
            "yaw": 0.8
        },
        "gender": {
            "male": -0.03,
            "female": 1.03
        },
        "makeup": {
            "eyeMakeup": 0.94,
            "lipMakeup": 0.76
        },
        "emotion": {
            "anger": -0.0,
            "contempt": 0.03,
            "disgust": 0.02,
            "fear": 0.0,
            "happiness": 0.39,
            "neutral": 0.47,
            "sadness": 0.06,
            "surprise": 0.04
        },
        "facialHair": {
            "moustache": -0.02,
            "beard": -0.02,
            "sideburns": -0.03
        },
        "hair": {
            "hairColor": [
                {
                    "name": "brown",
                    "confidence": 1.01
                },
                {
                    "name": "black",
                    "confidence": 0.31
                },
                {
                    "name": "blond",
                    "confidence": 0.48
                },
                {
                    "name": "red",
                    "confidence": 0.54
                },
                {
                    "name": "gray",
                    "confidence": 0.16
                },
                {
                    "name": "other",
                    "confidence": 0.07
                }
            ],
            "hairLength": [
                {
                    "name": "Long",
                    "confidence": 0.15
                },
                {
                    "name": "Medium",
                    "confidence": 0.17
                },
                {
                    "name": "Short",
                    "confidence": 0.12
                }
            ],
            "bald": 0.06
        },
        "occlusion": {
            "foreheadOccluded": -0.04,
            "eyeOccluded": -0.0,
            "mouthOccluded": -0.0
        },
        "ethnicity": [
            {
                "name": "asian",
                "confidence": 0.01
            },
            {
                "name": "black",
                "confidence": 0.0
            },
            {
                "name": "latino",
                "confidence": 0.0
            },
            {
                "name": "white",
                "confidence": 0.98
            }
        ],
        "eye_color": [
            {
                "name": "Blue",
                "confidence": 0.02
            },
            {
                "name": "Brown",
                "confidence": 0.49
            },
            {
                "name": "Green",
                "confidence": 0.5
            },
            {
                "name": "Grey",
                "confidence": 0.08
            }
        ],
        "smile": 0.39,
        "age": 33.32
    },
    "bug_probability": 0.02
}