{
    "image": "generated.photos_v3_0759817_0742496_0732614.jpg",
    "faceLandmarks": {
        "mouth": [
            {
                "x": 98,
                "y": 188
            },
            {
                "x": 106,
                "y": 180
            },
            {
                "x": 116,
                "y": 176
            },
            {
                "x": 122,
                "y": 180
            },
            {
                "x": 130,
                "y": 176
            },
            {
                "x": 142,
                "y": 182
            },
            {
                "x": 154,
                "y": 188
            },
            {
                "x": 142,
                "y": 198
            },
            {
                "x": 130,
                "y": 202
            },
            {
                "x": 122,
                "y": 204
            },
            {
                "x": 114,
                "y": 202
            },
            {
                "x": 106,
                "y": 198
            },
            {
                "x": 104,
                "y": 188
            },
            {
                "x": 116,
                "y": 188
            },
            {
                "x": 122,
                "y": 188
            },
            {
                "x": 130,
                "y": 188
            },
            {
                "x": 148,
                "y": 188
            },
            {
                "x": 130,
                "y": 188
            },
            {
                "x": 122,
                "y": 190
            },
            {
                "x": 116,
                "y": 188
            }
        ],
        "right_eyebrow": [
            {
                "x": 74,
                "y": 104
            },
            {
                "x": 80,
                "y": 96
            },
            {
                "x": 90,
                "y": 96
            },
            {
                "x": 102,
                "y": 96
            },
            {
                "x": 110,
                "y": 102
            }
        ],
        "left_eyebrow": [
            {
                "x": 136,
                "y": 102
            },
            {
                "x": 148,
                "y": 96
            },
            {
                "x": 160,
                "y": 94
            },
            {
                "x": 174,
                "y": 96
            },
            {
                "x": 184,
                "y": 104
            }
        ],
        "right_eye": [
            {
                "x": 84,
                "y": 120
            },
            {
                "x": 90,
                "y": 116
            },
            {
                "x": 100,
                "y": 116
            },
            {
                "x": 108,
                "y": 122
            },
            {
                "x": 100,
                "y": 124
            },
            {
                "x": 90,
                "y": 124
            }
        ],
        "left_eye": [
            {
                "x": 144,
                "y": 122
            },
            {
                "x": 152,
                "y": 116
            },
            {
                "x": 162,
                "y": 116
            },
            {
                "x": 170,
                "y": 120
            },
            {
                "x": 164,
                "y": 124
            },
            {
                "x": 152,
                "y": 124
            }
        ],
        "nose": [
            {
                "x": 124,
                "y": 118
            },
            {
                "x": 124,
                "y": 128
            },
            {
                "x": 122,
                "y": 138
            },
            {
                "x": 122,
                "y": 150
            },
            {
                "x": 110,
                "y": 160
            },
            {
                "x": 116,
                "y": 162
            },
            {
                "x": 124,
                "y": 164
            },
            {
                "x": 132,
                "y": 162
            }
        ],
        "jaw": [
            {
                "x": 68,
                "y": 122
            },
            {
                "x": 68,
                "y": 140
            },
            {
                "x": 70,
                "y": 158
            },
            {
                "x": 72,
                "y": 174
            },
            {
                "x": 78,
                "y": 192
            },
            {
                "x": 86,
                "y": 208
            },
            {
                "x": 96,
                "y": 222
            },
            {
                "x": 110,
                "y": 234
            },
            {
                "x": 128,
                "y": 238
            },
            {
                "x": 148,
                "y": 234
            },
            {
                "x": 166,
                "y": 224
            },
            {
                "x": 182,
                "y": 212
            },
            {
                "x": 196,
                "y": 196
            },
            {
                "x": 204,
                "y": 178
            },
            {
                "x": 208,
                "y": 158
            },
            {
                "x": 208,
                "y": 136
            },
            {
                "x": 208,
                "y": 116
            }
        ]
    },
    "faceAttributes": {
        "headPose": {
            "pitch": -1.72,
            "roll": -0.4,
            "yaw": -10.54
        },
        "gender": {
            "male": 0.94,
            "female": 0.06
        },
        "makeup": {
            "eyeMakeup": 0.02,
            "lipMakeup": 0.03
        },
        "emotion": {
            "anger": 0.01,
            "contempt": 0.02,
            "disgust": 0.02,
            "fear": -0.0,
            "happiness": 0.39,
            "neutral": 0.53,
            "sadness": 0.03,
            "surprise": 0.01
        },
        "facialHair": {
            "moustache": 0.16,
            "beard": 0.17,
            "sideburns": 0.1
        },
        "hair": {
            "hairColor": [
                {
                    "name": "brown",
                    "confidence": 0.86
                },
                {
                    "name": "black",
                    "confidence": 0.87
                },
                {
                    "name": "blond",
                    "confidence": 0.18
                },
                {
                    "name": "red",
                    "confidence": 0.11
                },
                {
                    "name": "gray",
                    "confidence": 0.38
                },
                {
                    "name": "other",
                    "confidence": 0.28
                }
            ],
            "hairLength": [
                {
                    "name": "Long",
                    "confidence": 0.0
                },
                {
                    "name": "Medium",
                    "confidence": 0.03
                },
                {
                    "name": "Short",
                    "confidence": 1.0
                }
            ],
            "bald": 0.16
        },
        "occlusion": {
            "foreheadOccluded": 0.02,
            "eyeOccluded": 0.0,
            "mouthOccluded": 0.0
        },
        "ethnicity": [
            {
                "name": "asian",
                "confidence": 0.01
            },
            {
                "name": "black",
                "confidence": 0.88
            },
            {
                "name": "latino",
                "confidence": 0.1
            },
            {
                "name": "white",
                "confidence": 0.0
            }
        ],
        "eye_color": [
            {
                "name": "Blue",
                "confidence": 0.02
            },
            {
                "name": "Brown",
                "confidence": 0.98
            },
            {
                "name": "Green",
                "confidence": 0.01
            },
            {
                "name": "Grey",
                "confidence": 0.01
            }
        ],
        "smile": 0.39,
        "age": 24.27
    },
    "bug_probability": 0.03
}