{
    "image": "generated.photos_v3_0456336.jpg",
    "faceLandmarks": {
        "mouth": [
            {
                "x": 104,
                "y": 188
            },
            {
                "x": 114,
                "y": 184
            },
            {
                "x": 124,
                "y": 182
            },
            {
                "x": 130,
                "y": 184
            },
            {
                "x": 134,
                "y": 182
            },
            {
                "x": 142,
                "y": 184
            },
            {
                "x": 150,
                "y": 190
            },
            {
                "x": 142,
                "y": 196
            },
            {
                "x": 136,
                "y": 200
            },
            {
                "x": 130,
                "y": 200
            },
            {
                "x": 122,
                "y": 200
            },
            {
                "x": 114,
                "y": 196
            },
            {
                "x": 110,
                "y": 188
            },
            {
                "x": 124,
                "y": 188
            },
            {
                "x": 130,
                "y": 190
            },
            {
                "x": 134,
                "y": 188
            },
            {
                "x": 146,
                "y": 190
            },
            {
                "x": 134,
                "y": 188
            },
            {
                "x": 130,
                "y": 190
            },
            {
                "x": 124,
                "y": 188
            }
        ],
        "right_eyebrow": [
            {
                "x": 70,
                "y": 106
            },
            {
                "x": 82,
                "y": 100
            },
            {
                "x": 94,
                "y": 98
            },
            {
                "x": 106,
                "y": 102
            },
            {
                "x": 118,
                "y": 108
            }
        ],
        "left_eyebrow": [
            {
                "x": 140,
                "y": 108
            },
            {
                "x": 150,
                "y": 102
            },
            {
                "x": 162,
                "y": 100
            },
            {
                "x": 172,
                "y": 100
            },
            {
                "x": 180,
                "y": 106
            }
        ],
        "right_eye": [
            {
                "x": 86,
                "y": 120
            },
            {
                "x": 94,
                "y": 116
            },
            {
                "x": 102,
                "y": 116
            },
            {
                "x": 112,
                "y": 124
            },
            {
                "x": 102,
                "y": 126
            },
            {
                "x": 92,
                "y": 126
            }
        ],
        "left_eye": [
            {
                "x": 144,
                "y": 124
            },
            {
                "x": 150,
                "y": 116
            },
            {
                "x": 160,
                "y": 114
            },
            {
                "x": 166,
                "y": 120
            },
            {
                "x": 160,
                "y": 124
            },
            {
                "x": 152,
                "y": 124
            }
        ],
        "nose": [
            {
                "x": 130,
                "y": 120
            },
            {
                "x": 130,
                "y": 132
            },
            {
                "x": 130,
                "y": 144
            },
            {
                "x": 130,
                "y": 156
            },
            {
                "x": 118,
                "y": 164
            },
            {
                "x": 124,
                "y": 166
            },
            {
                "x": 130,
                "y": 168
            },
            {
                "x": 136,
                "y": 166
            }
        ],
        "jaw": [
            {
                "x": 54,
                "y": 116
            },
            {
                "x": 56,
                "y": 136
            },
            {
                "x": 58,
                "y": 154
            },
            {
                "x": 62,
                "y": 172
            },
            {
                "x": 68,
                "y": 190
            },
            {
                "x": 78,
                "y": 204
            },
            {
                "x": 92,
                "y": 218
            },
            {
                "x": 108,
                "y": 228
            },
            {
                "x": 126,
                "y": 230
            },
            {
                "x": 142,
                "y": 226
            },
            {
                "x": 156,
                "y": 214
            },
            {
                "x": 166,
                "y": 200
            },
            {
                "x": 174,
                "y": 186
            },
            {
                "x": 178,
                "y": 168
            },
            {
                "x": 182,
                "y": 152
            },
            {
                "x": 184,
                "y": 136
            },
            {
                "x": 184,
                "y": 118
            }
        ]
    },
    "faceAttributes": {
        "headPose": {
            "pitch": -5.92,
            "roll": 0.47,
            "yaw": 6.69
        },
        "gender": {
            "male": 0.3,
            "female": 0.7
        },
        "makeup": {
            "eyeMakeup": 0.8,
            "lipMakeup": 0.59
        },
        "emotion": {
            "anger": 0.01,
            "contempt": 0.04,
            "disgust": 0.02,
            "fear": 0.0,
            "happiness": 0.17,
            "neutral": 0.66,
            "sadness": 0.07,
            "surprise": 0.05
        },
        "facialHair": {
            "moustache": 0.01,
            "beard": 0.01,
            "sideburns": 0.01
        },
        "hair": {
            "hairColor": [
                {
                    "name": "brown",
                    "confidence": 0.96
                },
                {
                    "name": "black",
                    "confidence": 0.74
                },
                {
                    "name": "blond",
                    "confidence": 0.17
                },
                {
                    "name": "red",
                    "confidence": 0.29
                },
                {
                    "name": "gray",
                    "confidence": 0.2
                },
                {
                    "name": "other",
                    "confidence": 0.19
                }
            ],
            "hairLength": [
                {
                    "name": "Long",
                    "confidence": 0.01
                },
                {
                    "name": "Medium",
                    "confidence": 0.81
                },
                {
                    "name": "Short",
                    "confidence": 0.28
                }
            ],
            "bald": 0.12
        },
        "occlusion": {
            "foreheadOccluded": 0.0,
            "eyeOccluded": -0.0,
            "mouthOccluded": -0.0
        },
        "ethnicity": [
            {
                "name": "asian",
                "confidence": 0.04
            },
            {
                "name": "black",
                "confidence": 0.0
            },
            {
                "name": "latino",
                "confidence": 0.14
            },
            {
                "name": "white",
                "confidence": 0.82
            }
        ],
        "eye_color": [
            {
                "name": "Blue",
                "confidence": 0.04
            },
            {
                "name": "Brown",
                "confidence": 0.66
            },
            {
                "name": "Green",
                "confidence": 0.19
            },
            {
                "name": "Grey",
                "confidence": 0.1
            }
        ],
        "smile": 0.17,
        "age": 31.85
    },
    "bug_probability": 0.02
}