{
    "image": "generated.photos_v3_0482858.jpg",
    "faceLandmarks": {
        "mouth": [
            {
                "x": 102,
                "y": 188
            },
            {
                "x": 110,
                "y": 182
            },
            {
                "x": 120,
                "y": 180
            },
            {
                "x": 128,
                "y": 182
            },
            {
                "x": 134,
                "y": 180
            },
            {
                "x": 144,
                "y": 182
            },
            {
                "x": 152,
                "y": 188
            },
            {
                "x": 144,
                "y": 196
            },
            {
                "x": 136,
                "y": 198
            },
            {
                "x": 128,
                "y": 200
            },
            {
                "x": 120,
                "y": 198
            },
            {
                "x": 110,
                "y": 194
            },
            {
                "x": 106,
                "y": 188
            },
            {
                "x": 120,
                "y": 188
            },
            {
                "x": 128,
                "y": 190
            },
            {
                "x": 134,
                "y": 188
            },
            {
                "x": 148,
                "y": 190
            },
            {
                "x": 136,
                "y": 188
            },
            {
                "x": 128,
                "y": 190
            },
            {
                "x": 120,
                "y": 188
            }
        ],
        "right_eyebrow": [
            {
                "x": 70,
                "y": 112
            },
            {
                "x": 76,
                "y": 100
            },
            {
                "x": 90,
                "y": 94
            },
            {
                "x": 104,
                "y": 96
            },
            {
                "x": 118,
                "y": 100
            }
        ],
        "left_eyebrow": [
            {
                "x": 136,
                "y": 98
            },
            {
                "x": 150,
                "y": 94
            },
            {
                "x": 164,
                "y": 94
            },
            {
                "x": 178,
                "y": 100
            },
            {
                "x": 182,
                "y": 114
            }
        ],
        "right_eye": [
            {
                "x": 84,
                "y": 120
            },
            {
                "x": 92,
                "y": 116
            },
            {
                "x": 102,
                "y": 116
            },
            {
                "x": 110,
                "y": 122
            },
            {
                "x": 100,
                "y": 124
            },
            {
                "x": 92,
                "y": 124
            }
        ],
        "left_eye": [
            {
                "x": 144,
                "y": 122
            },
            {
                "x": 152,
                "y": 116
            },
            {
                "x": 162,
                "y": 116
            },
            {
                "x": 168,
                "y": 122
            },
            {
                "x": 162,
                "y": 124
            },
            {
                "x": 152,
                "y": 124
            }
        ],
        "nose": [
            {
                "x": 128,
                "y": 116
            },
            {
                "x": 128,
                "y": 126
            },
            {
                "x": 128,
                "y": 138
            },
            {
                "x": 128,
                "y": 150
            },
            {
                "x": 114,
                "y": 162
            },
            {
                "x": 122,
                "y": 162
            },
            {
                "x": 128,
                "y": 164
            },
            {
                "x": 134,
                "y": 162
            }
        ],
        "jaw": [
            {
                "x": 62,
                "y": 126
            },
            {
                "x": 62,
                "y": 144
            },
            {
                "x": 64,
                "y": 162
            },
            {
                "x": 68,
                "y": 180
            },
            {
                "x": 72,
                "y": 198
            },
            {
                "x": 80,
                "y": 212
            },
            {
                "x": 92,
                "y": 226
            },
            {
                "x": 108,
                "y": 236
            },
            {
                "x": 128,
                "y": 238
            },
            {
                "x": 146,
                "y": 236
            },
            {
                "x": 162,
                "y": 224
            },
            {
                "x": 174,
                "y": 212
            },
            {
                "x": 182,
                "y": 196
            },
            {
                "x": 186,
                "y": 180
            },
            {
                "x": 188,
                "y": 162
            },
            {
                "x": 192,
                "y": 144
            },
            {
                "x": 192,
                "y": 126
            }
        ]
    },
    "faceAttributes": {
        "headPose": {
            "pitch": 3.55,
            "roll": 0.18,
            "yaw": -1.09
        },
        "gender": {
            "male": 0.93,
            "female": 0.07
        },
        "makeup": {
            "eyeMakeup": 0.41,
            "lipMakeup": 0.26
        },
        "emotion": {
            "anger": -0.0,
            "contempt": 0.03,
            "disgust": 0.01,
            "fear": -0.0,
            "happiness": 0.36,
            "neutral": 0.56,
            "sadness": 0.02,
            "surprise": 0.02
        },
        "facialHair": {
            "moustache": 0.32,
            "beard": 0.32,
            "sideburns": 0.24
        },
        "hair": {
            "hairColor": [
                {
                    "name": "brown",
                    "confidence": 0.9
                },
                {
                    "name": "black",
                    "confidence": 0.97
                },
                {
                    "name": "blond",
                    "confidence": 0.05
                },
                {
                    "name": "red",
                    "confidence": 0.1
                },
                {
                    "name": "gray",
                    "confidence": 0.33
                },
                {
                    "name": "other",
                    "confidence": 0.31
                }
            ],
            "hairLength": [
                {
                    "name": "Long",
                    "confidence": 0.01
                },
                {
                    "name": "Medium",
                    "confidence": 0.01
                },
                {
                    "name": "Short",
                    "confidence": 1.0
                }
            ],
            "bald": 0.12
        },
        "occlusion": {
            "foreheadOccluded": -0.0,
            "eyeOccluded": -0.0,
            "mouthOccluded": -0.0
        },
        "ethnicity": [
            {
                "name": "asian",
                "confidence": 0.11
            },
            {
                "name": "black",
                "confidence": 0.0
            },
            {
                "name": "latino",
                "confidence": 0.76
            },
            {
                "name": "white",
                "confidence": 0.12
            }
        ],
        "eye_color": [
            {
                "name": "Blue",
                "confidence": 0.0
            },
            {
                "name": "Brown",
                "confidence": 0.99
            },
            {
                "name": "Green",
                "confidence": 0.04
            },
            {
                "name": "Grey",
                "confidence": 0.01
            }
        ],
        "smile": 0.36,
        "age": 26.35
    },
    "bug_probability": 0.0
}