{
    "image": "generated.photos_v3_0465765_0438527_0322513.jpg",
    "faceLandmarks": {
        "mouth": [
            {
                "x": 98,
                "y": 186
            },
            {
                "x": 106,
                "y": 178
            },
            {
                "x": 116,
                "y": 176
            },
            {
                "x": 124,
                "y": 178
            },
            {
                "x": 130,
                "y": 176
            },
            {
                "x": 142,
                "y": 178
            },
            {
                "x": 154,
                "y": 184
            },
            {
                "x": 144,
                "y": 196
            },
            {
                "x": 132,
                "y": 200
            },
            {
                "x": 124,
                "y": 200
            },
            {
                "x": 116,
                "y": 200
            },
            {
                "x": 106,
                "y": 194
            },
            {
                "x": 104,
                "y": 186
            },
            {
                "x": 116,
                "y": 184
            },
            {
                "x": 124,
                "y": 186
            },
            {
                "x": 132,
                "y": 184
            },
            {
                "x": 150,
                "y": 186
            },
            {
                "x": 132,
                "y": 186
            },
            {
                "x": 124,
                "y": 186
            },
            {
                "x": 116,
                "y": 186
            }
        ],
        "right_eyebrow": [
            {
                "x": 74,
                "y": 104
            },
            {
                "x": 80,
                "y": 96
            },
            {
                "x": 88,
                "y": 94
            },
            {
                "x": 98,
                "y": 94
            },
            {
                "x": 108,
                "y": 98
            }
        ],
        "left_eyebrow": [
            {
                "x": 140,
                "y": 100
            },
            {
                "x": 150,
                "y": 96
            },
            {
                "x": 162,
                "y": 94
            },
            {
                "x": 174,
                "y": 98
            },
            {
                "x": 182,
                "y": 106
            }
        ],
        "right_eye": [
            {
                "x": 84,
                "y": 122
            },
            {
                "x": 90,
                "y": 116
            },
            {
                "x": 100,
                "y": 116
            },
            {
                "x": 108,
                "y": 122
            },
            {
                "x": 98,
                "y": 124
            },
            {
                "x": 90,
                "y": 124
            }
        ],
        "left_eye": [
            {
                "x": 144,
                "y": 122
            },
            {
                "x": 152,
                "y": 116
            },
            {
                "x": 162,
                "y": 116
            },
            {
                "x": 168,
                "y": 120
            },
            {
                "x": 162,
                "y": 124
            },
            {
                "x": 152,
                "y": 124
            }
        ],
        "nose": [
            {
                "x": 124,
                "y": 118
            },
            {
                "x": 124,
                "y": 128
            },
            {
                "x": 122,
                "y": 138
            },
            {
                "x": 122,
                "y": 150
            },
            {
                "x": 108,
                "y": 158
            },
            {
                "x": 116,
                "y": 160
            },
            {
                "x": 122,
                "y": 162
            },
            {
                "x": 130,
                "y": 160
            }
        ],
        "jaw": [
            {
                "x": 68,
                "y": 122
            },
            {
                "x": 68,
                "y": 138
            },
            {
                "x": 68,
                "y": 156
            },
            {
                "x": 72,
                "y": 172
            },
            {
                "x": 76,
                "y": 188
            },
            {
                "x": 84,
                "y": 202
            },
            {
                "x": 94,
                "y": 216
            },
            {
                "x": 108,
                "y": 226
            },
            {
                "x": 126,
                "y": 230
            },
            {
                "x": 146,
                "y": 228
            },
            {
                "x": 164,
                "y": 220
            },
            {
                "x": 178,
                "y": 208
            },
            {
                "x": 190,
                "y": 192
            },
            {
                "x": 196,
                "y": 176
            },
            {
                "x": 200,
                "y": 156
            },
            {
                "x": 200,
                "y": 138
            },
            {
                "x": 202,
                "y": 118
            }
        ]
    },
    "faceAttributes": {
        "headPose": {
            "pitch": -0.9,
            "roll": -0.43,
            "yaw": -10.01
        },
        "gender": {
            "male": 0.94,
            "female": 0.06
        },
        "makeup": {
            "eyeMakeup": -0.02,
            "lipMakeup": 0.02
        },
        "emotion": {
            "anger": 0.0,
            "contempt": 0.02,
            "disgust": 0.02,
            "fear": -0.0,
            "happiness": 0.38,
            "neutral": 0.54,
            "sadness": 0.03,
            "surprise": 0.01
        },
        "facialHair": {
            "moustache": 0.21,
            "beard": 0.23,
            "sideburns": 0.13
        },
        "hair": {
            "hairColor": [
                {
                    "name": "brown",
                    "confidence": 0.85
                },
                {
                    "name": "black",
                    "confidence": 0.91
                },
                {
                    "name": "blond",
                    "confidence": 0.15
                },
                {
                    "name": "red",
                    "confidence": 0.09
                },
                {
                    "name": "gray",
                    "confidence": 0.41
                },
                {
                    "name": "other",
                    "confidence": 0.32
                }
            ],
            "hairLength": [
                {
                    "name": "Long",
                    "confidence": 0.01
                },
                {
                    "name": "Medium",
                    "confidence": 0.04
                },
                {
                    "name": "Short",
                    "confidence": 0.99
                }
            ],
            "bald": 0.23
        },
        "occlusion": {
            "foreheadOccluded": 0.03,
            "eyeOccluded": 0.0,
            "mouthOccluded": 0.0
        },
        "ethnicity": [
            {
                "name": "asian",
                "confidence": 0.03
            },
            {
                "name": "black",
                "confidence": 0.81
            },
            {
                "name": "latino",
                "confidence": 0.16
            },
            {
                "name": "white",
                "confidence": 0.01
            }
        ],
        "eye_color": [
            {
                "name": "Blue",
                "confidence": 0.03
            },
            {
                "name": "Brown",
                "confidence": 0.97
            },
            {
                "name": "Green",
                "confidence": 0.0
            },
            {
                "name": "Grey",
                "confidence": 0.01
            }
        ],
        "smile": 0.38,
        "age": 27.56
    },
    "bug_probability": 0.0
}