{
    "image": "generated.photos_v3_0810443.jpg",
    "faceLandmarks": {
        "mouth": [
            {
                "x": 104,
                "y": 192
            },
            {
                "x": 108,
                "y": 184
            },
            {
                "x": 116,
                "y": 178
            },
            {
                "x": 120,
                "y": 182
            },
            {
                "x": 128,
                "y": 180
            },
            {
                "x": 138,
                "y": 184
            },
            {
                "x": 146,
                "y": 190
            },
            {
                "x": 138,
                "y": 200
            },
            {
                "x": 130,
                "y": 204
            },
            {
                "x": 122,
                "y": 204
            },
            {
                "x": 116,
                "y": 204
            },
            {
                "x": 110,
                "y": 200
            },
            {
                "x": 108,
                "y": 192
            },
            {
                "x": 116,
                "y": 188
            },
            {
                "x": 122,
                "y": 190
            },
            {
                "x": 128,
                "y": 188
            },
            {
                "x": 142,
                "y": 192
            },
            {
                "x": 128,
                "y": 190
            },
            {
                "x": 122,
                "y": 190
            },
            {
                "x": 116,
                "y": 190
            }
        ],
        "right_eyebrow": [
            {
                "x": 80,
                "y": 106
            },
            {
                "x": 84,
                "y": 96
            },
            {
                "x": 92,
                "y": 94
            },
            {
                "x": 102,
                "y": 96
            },
            {
                "x": 110,
                "y": 100
            }
        ],
        "left_eyebrow": [
            {
                "x": 128,
                "y": 100
            },
            {
                "x": 142,
                "y": 96
            },
            {
                "x": 156,
                "y": 94
            },
            {
                "x": 170,
                "y": 96
            },
            {
                "x": 182,
                "y": 106
            }
        ],
        "right_eye": [
            {
                "x": 90,
                "y": 122
            },
            {
                "x": 94,
                "y": 116
            },
            {
                "x": 104,
                "y": 116
            },
            {
                "x": 112,
                "y": 122
            },
            {
                "x": 104,
                "y": 126
            },
            {
                "x": 94,
                "y": 126
            }
        ],
        "left_eye": [
            {
                "x": 142,
                "y": 122
            },
            {
                "x": 148,
                "y": 114
            },
            {
                "x": 158,
                "y": 114
            },
            {
                "x": 166,
                "y": 120
            },
            {
                "x": 160,
                "y": 124
            },
            {
                "x": 150,
                "y": 124
            }
        ],
        "nose": [
            {
                "x": 120,
                "y": 118
            },
            {
                "x": 120,
                "y": 130
            },
            {
                "x": 118,
                "y": 140
            },
            {
                "x": 116,
                "y": 152
            },
            {
                "x": 108,
                "y": 162
            },
            {
                "x": 114,
                "y": 164
            },
            {
                "x": 120,
                "y": 166
            },
            {
                "x": 126,
                "y": 164
            }
        ],
        "jaw": [
            {
                "x": 78,
                "y": 126
            },
            {
                "x": 78,
                "y": 142
            },
            {
                "x": 80,
                "y": 158
            },
            {
                "x": 84,
                "y": 174
            },
            {
                "x": 88,
                "y": 190
            },
            {
                "x": 94,
                "y": 206
            },
            {
                "x": 100,
                "y": 222
            },
            {
                "x": 110,
                "y": 234
            },
            {
                "x": 126,
                "y": 238
            },
            {
                "x": 144,
                "y": 236
            },
            {
                "x": 164,
                "y": 228
            },
            {
                "x": 180,
                "y": 216
            },
            {
                "x": 194,
                "y": 202
            },
            {
                "x": 202,
                "y": 184
            },
            {
                "x": 206,
                "y": 166
            },
            {
                "x": 208,
                "y": 146
            },
            {
                "x": 206,
                "y": 126
            }
        ]
    },
    "faceAttributes": {
        "headPose": {
            "pitch": -2.42,
            "roll": -0.73,
            "yaw": -19.71
        },
        "gender": {
            "male": 0.64,
            "female": 0.36
        },
        "makeup": {
            "eyeMakeup": 0.57,
            "lipMakeup": 0.41
        },
        "emotion": {
            "anger": 0.01,
            "contempt": 0.03,
            "disgust": 0.02,
            "fear": 0.0,
            "happiness": 0.31,
            "neutral": 0.56,
            "sadness": 0.02,
            "surprise": 0.04
        },
        "facialHair": {
            "moustache": 0.2,
            "beard": 0.21,
            "sideburns": 0.15
        },
        "hair": {
            "hairColor": [
                {
                    "name": "brown",
                    "confidence": 0.9
                },
                {
                    "name": "black",
                    "confidence": 0.92
                },
                {
                    "name": "blond",
                    "confidence": 0.03
                },
                {
                    "name": "red",
                    "confidence": 0.16
                },
                {
                    "name": "gray",
                    "confidence": 0.29
                },
                {
                    "name": "other",
                    "confidence": 0.28
                }
            ],
            "hairLength": [
                {
                    "name": "Long",
                    "confidence": 0.01
                },
                {
                    "name": "Medium",
                    "confidence": 0.15
                },
                {
                    "name": "Short",
                    "confidence": 0.93
                }
            ],
            "bald": 0.12
        },
        "occlusion": {
            "foreheadOccluded": 0.05,
            "eyeOccluded": 0.0,
            "mouthOccluded": 0.0
        },
        "ethnicity": [
            {
                "name": "asian",
                "confidence": 0.03
            },
            {
                "name": "black",
                "confidence": 0.05
            },
            {
                "name": "latino",
                "confidence": 0.74
            },
            {
                "name": "white",
                "confidence": 0.18
            }
        ],
        "eye_color": [
            {
                "name": "Blue",
                "confidence": 0.01
            },
            {
                "name": "Brown",
                "confidence": 0.97
            },
            {
                "name": "Green",
                "confidence": 0.03
            },
            {
                "name": "Grey",
                "confidence": 0.03
            }
        ],
        "smile": 0.31,
        "age": 31.46
    },
    "bug_probability": 0.03
}